{"kind":"identitytoolkit#DownloadAccountResponse","users":[{"localId":"dfgERkyw7iupenmQZ2ZMvha20hKg","createdAt":"1647561317479","lastLoginAt":"1650215113087","displayName":"john110","passwordHash":"fakeHash:salt=fakeSaltvJbuTs7Ayt4gvsjzBaYZ:password=passwordA1","salt":"fakeSaltvJbuTs7Ayt4gvsjzBaYZ","passwordUpdatedAt":1650215063645,"providerUserInfo":[{"providerId":"password","email":"john@acme.com","federatedId":"john@acme.com","rawId":"john@acme.com","displayName":"john110"}],"validSince":"1650215063","email":"john@acme.com","emailVerified":false,"disabled":false,"lastRefreshAt":"2022-04-17T17:05:13.087Z"}]}